sicaptcha/__init__.py
sicaptcha/sicaptcha.py
sicaptcha-0.0.7.dist-info/METADATA
sicaptcha-0.0.7.dist-info/WHEEL
sicaptcha-0.0.7.dist-info/top_level.txt
sicaptcha-0.0.7.dist-info/RECORD
